[
  {
    "channel_link": "https://d.daddylivehd.sx/embed/stream-35.php",
    "channel_logo": "https://cdn.britannica.com/51/190751-050-147B93F7/soccer-ball-goal.jpg",
    "channels_name": "Portsmouth vs Bolton Wanderers",
    "category_name": "⚽ Soccer"
  },
  {
    "channel_link": "https://d.daddylivehd.sx/embed/stream-38.php",
    "channel_logo": "https://cdn.britannica.com/51/190751-050-147B93F7/soccer-ball-goal.jpg",
    "channels_name": "Portsmouth vs Bolton Wanderers",
    "category_name": "⚽ Soccer"
  },
  {
    "channel_link": "https://d.daddylivehd.sx/embed/stream-628.php",
    "channel_logo": "https://cdn.britannica.com/51/190751-050-147B93F7/soccer-ball-goal.jpg",
    "channels_name": "Portsmouth vs Bolton Wanderers",
    "category_name": "⚽ Soccer"
  },
  {
    "channel_link": "https://d.daddylivehd.sx/embed/stream-102.php",
    "channel_logo": "https://cdn.britannica.com/51/190751-050-147B93F7/soccer-ball-goal.jpg",
    "channels_name": "Maziya vs Mohun Bagan",
    "category_name": "⚽ Soccer"
  },
  {
    "channel_link": "https://d.daddylivehd.sx/embed/stream-465.php",
    "channel_logo": "https://cdn.britannica.com/51/190751-050-147B93F7/soccer-ball-goal.jpg",
    "channels_name": "Yantra 2019 vs Spartak Varna",
    "category_name": "⚽ Soccer"
  },
  {
    "channel_link": "https://d.daddylivehd.sx/embed/stream-453.php",
    "channel_logo": "https://cdn.britannica.com/51/190751-050-147B93F7/soccer-ball-goal.jpg",
    "channels_name": "Yantra 2019 vs Spartak Varna",
    "category_name": "⚽ Soccer"
  },
  {
    "channel_link": "https://d.daddylivehd.sx/embed/stream-1.php",
    "channel_logo": "https://cdn.britannica.com/51/190751-050-147B93F7/soccer-ball-goal.jpg",
    "channels_name": "Abha vs Al Khaleej",
    "category_name": "⚽ Soccer"
  },
  {
    "channel_link": "https://d.daddylivehd.sx/embed/stream-756.php",
    "channel_logo": "https://cdn.britannica.com/51/190751-050-147B93F7/soccer-ball-goal.jpg",
    "channels_name": "Abha vs Al Khaleej",
    "category_name": "⚽ Soccer"
  },
  {
    "channel_link": "https://d.daddylivehd.sx/embed/stream-426.php",
    "channel_logo": "https://cdn.britannica.com/51/190751-050-147B93F7/soccer-ball-goal.jpg",
    "channels_name": "Abha vs Al Khaleej",
    "category_name": "⚽ Soccer"
  },
  {
    "channel_link": "https://d.daddylivehd.sx/embed/stream-465.php",
    "channel_logo": "https://cdn.britannica.com/51/190751-050-147B93F7/soccer-ball-goal.jpg",
    "channels_name": "Lokomotiv Plovdiv vs Pirin Blagoevgrad",
    "category_name": "⚽ Soccer"
  },
  {
    "channel_link": "https://d.daddylivehd.sx/embed/stream-102.php",
    "channel_logo": "https://cdn.britannica.com/51/190751-050-147B93F7/soccer-ball-goal.jpg",
    "channels_name": "Lokomotiv Plovdiv vs Pirin Blagoevgrad",
    "category_name": "⚽ Soccer"
  },
  {
    "channel_link": "https://d.daddylivehd.sx/embed/stream-468.php",
    "channel_logo": "https://cdn.britannica.com/51/190751-050-147B93F7/soccer-ball-goal.jpg",
    "channels_name": "Odisha vs Bashundhara Kings",
    "category_name": "⚽ Soccer"
  },
  {
    "channel_link": "https://d.daddylivehd.sx/embed/stream-453.php",
    "channel_logo": "https://cdn.britannica.com/51/190751-050-147B93F7/soccer-ball-goal.jpg",
    "channels_name": "Odisha vs Bashundhara Kings",
    "category_name": "⚽ Soccer"
  },
  {
    "channel_link": "https://d.daddylivehd.sx/embed/stream-2.php",
    "channel_logo": "https://cdn.britannica.com/51/190751-050-147B93F7/soccer-ball-goal.jpg",
    "channels_name": "Al Hilal vs Al Taawon",
    "category_name": "⚽ Soccer"
  },
  {
    "channel_link": "https://d.daddylivehd.sx/embed/stream-756.php",
    "channel_logo": "https://cdn.britannica.com/51/190751-050-147B93F7/soccer-ball-goal.jpg",
    "channels_name": "Al Hilal vs Al Taawon",
    "category_name": "⚽ Soccer"
  },
  {
    "channel_link": "https://d.daddylivehd.sx/embed/stream-463.php",
    "channel_logo": "https://cdn.britannica.com/51/190751-050-147B93F7/soccer-ball-goal.jpg",
    "channels_name": "Al Hilal vs Al Taawon",
    "category_name": "⚽ Soccer"
  },
  {
    "channel_link": "https://d.daddylivehd.sx/embed/stream-134.php",
    "channel_logo": "https://cdn.britannica.com/51/190751-050-147B93F7/soccer-ball-goal.jpg",
    "channels_name": "Radnicki Niš vs Partizan",
    "category_name": "⚽ Soccer"
  },
  {
    "channel_link": "https://d.daddylivehd.sx/embed/stream-143.php",
    "channel_logo": "https://cdn.britannica.com/51/190751-050-147B93F7/soccer-ball-goal.jpg",
    "channels_name": "Radnicki Niš vs Partizan",
    "category_name": "⚽ Soccer"
  },
  {
    "channel_link": "https://d.daddylivehd.sx/embed/stream-465.php",
    "channel_logo": "https://cdn.britannica.com/51/190751-050-147B93F7/soccer-ball-goal.jpg",
    "channels_name": "Beroe vs Etar",
    "category_name": "⚽ Soccer"
  },
  {
    "channel_link": "https://d.daddylivehd.sx/embed/stream-465.php",
    "channel_logo": "https://cdn.britannica.com/51/190751-050-147B93F7/soccer-ball-goal.jpg",
    "channels_name": "FC U Craiova 1948 vs Botosani",
    "category_name": "⚽ Soccer"
  },
  {
    "channel_link": "https://d.daddylivehd.sx/embed/stream-400.php",
    "channel_logo": "https://cdn.britannica.com/51/190751-050-147B93F7/soccer-ball-goal.jpg",
    "channels_name": "FC U Craiova 1948 vs Botosani",
    "category_name": "⚽ Soccer"
  },
  {
    "channel_link": "https://d.daddylivehd.sx/embed/stream-439.php",
    "channel_logo": "https://cdn.britannica.com/51/190751-050-147B93F7/soccer-ball-goal.jpg",
    "channels_name": "FC U Craiova 1948 vs Botosani",
    "category_name": "⚽ Soccer"
  },
  {
    "channel_link": "https://d.daddylivehd.sx/embed/stream-584.php",
    "channel_logo": "https://cdn.britannica.com/51/190751-050-147B93F7/soccer-ball-goal.jpg",
    "channels_name": "FC U Craiova 1948 vs Botosani",
    "category_name": "⚽ Soccer"
  },
  {
    "channel_link": "https://d.daddylivehd.sx/embed/stream-104.php",
    "channel_logo": "https://cdn.britannica.com/51/190751-050-147B93F7/soccer-ball-goal.jpg",
    "channels_name": "Al Kahrabaa vs Al Ittihad",
    "category_name": "⚽ Soccer"
  },
  {
    "channel_link": "https://d.daddylivehd.sx/embed/stream-468.php",
    "channel_logo": "https://cdn.britannica.com/51/190751-050-147B93F7/soccer-ball-goal.jpg",
    "channels_name": "Al Kahrabaa vs Al Ittihad",
    "category_name": "⚽ Soccer"
  },
  {
    "channel_link": "https://d.daddylivehd.sx/embed/stream-453.php",
    "channel_logo": "https://cdn.britannica.com/51/190751-050-147B93F7/soccer-ball-goal.jpg",
    "channels_name": "Al Wihdat vs Al Kuwait",
    "category_name": "⚽ Soccer"
  },
  {
    "channel_link": "https://d.daddylivehd.sx/embed/stream-2.php",
    "channel_logo": "https://cdn.britannica.com/51/190751-050-147B93F7/soccer-ball-goal.jpg",
    "channels_name": "Al Wihdat vs Al Kuwait",
    "category_name": "⚽ Soccer"
  },
  {
    "channel_link": "https://d.daddylivehd.sx/embed/stream-756.php",
    "channel_logo": "https://cdn.britannica.com/51/190751-050-147B93F7/soccer-ball-goal.jpg",
    "channels_name": "Al Wihdat vs Al Kuwait",
    "category_name": "⚽ Soccer"
  },
  {
    "channel_link": "https://d.daddylivehd.sx/embed/stream-463.php",
    "channel_logo": "https://cdn.britannica.com/51/190751-050-147B93F7/soccer-ball-goal.jpg",
    "channels_name": "Al Hilal vs Al Taawon",
    "category_name": "⚽ Soccer"
  },
  {
    "channel_link": "https://d.daddylivehd.sx/embed/stream-134.php",
    "channel_logo": "https://cdn.britannica.com/51/190751-050-147B93F7/soccer-ball-goal.jpg",
    "channels_name": "Al Hilal vs Al Taawon",
    "category_name": "⚽ Soccer"
  },
  {
    "channel_link": "https://d.daddylivehd.sx/embed/stream-2.php",
    "channel_logo": "https://cdn.britannica.com/51/190751-050-147B93F7/soccer-ball-goal.jpg",
    "channels_name": "Al Hilal vs Al Taawon",
    "category_name": "⚽ Soccer"
  },
  {
    "channel_link": "https://d.daddylivehd.sx/embed/stream-139.php",
    "channel_logo": "https://cdn.britannica.com/51/190751-050-147B93F7/soccer-ball-goal.jpg",
    "channels_name": "Vojvodina vs Napredak",
    "category_name": "⚽ Soccer"
  },
  {
    "channel_link": "https://d.daddylivehd.sx/embed/stream-31.php",
    "channel_logo": "https://cdn.britannica.com/51/190751-050-147B93F7/soccer-ball-goal.jpg",
    "channels_name": "Empoli vs Lecce",
    "category_name": "⚽ Soccer"
  },
  {
    "channel_link": "https://d.daddylivehd.sx/embed/stream-2.php",
    "channel_logo": "https://cdn.britannica.com/51/190751-050-147B93F7/soccer-ball-goal.jpg",
    "channels_name": "Al Shabab vs Al Nassr",
    "category_name": "⚽ Soccer"
  },
  {
    "channel_link": "https://d.daddylivehd.sx/embed/stream-48.php",
    "channel_logo": "https://cdn.britannica.com/51/190751-050-147B93F7/soccer-ball-goal.jpg",
    "channels_name": "Puszcza Niepolomice vs Widzew Lódz",
    "category_name": "⚽ Soccer"
  },
  {
    "channel_link": "https://d.daddylivehd.sx/embed/stream-143.php",
    "channel_logo": "https://cdn.britannica.com/51/190751-050-147B93F7/soccer-ball-goal.jpg",
    "channels_name": "Maccabi Netanya vs Hapoel Be'er Sheva",
    "category_name": "⚽ Soccer"
  },
  {
    "channel_link": "https://d.daddylivehd.sx/embed/stream-400.php",
    "channel_logo": "https://cdn.britannica.com/51/190751-050-147B93F7/soccer-ball-goal.jpg",
    "channels_name": "Dinamo Bucuresti vs Universitatea Cluj",
    "category_name": "⚽ Soccer"
  },
  {
    "channel_link": "https://d.daddylivehd.sx/embed/stream-6.php",
    "channel_logo": "https://cdn.britannica.com/51/190751-050-147B93F7/soccer-ball-goal.jpg",
    "channels_name": "Bayern München vs Bayer Leverkusen",
    "category_name": "⚽ Soccer"
  },
  {
    "channel_link": "https://d.daddylivehd.sx/embed/stream-379.php",
    "channel_logo": "https://cdn.britannica.com/51/190751-050-147B93F7/soccer-ball-goal.jpg",
    "channels_name": "AZ II vs Den Bosch",
    "category_name": "⚽ Soccer"
  },
  {
    "channel_link": "https://d.daddylivehd.sx/embed/stream-7.php",
    "channel_logo": "https://cdn.britannica.com/51/190751-050-147B93F7/soccer-ball-goal.jpg",
    "channels_name": "Taranto vs Monopoli",
    "category_name": "⚽ Soccer"
  },
  {
    "channel_link": "https://d.daddylivehd.sx/embed/stream-8.php",
    "channel_logo": "https://cdn.britannica.com/51/190751-050-147B93F7/soccer-ball-goal.jpg",
    "channels_name": "Virtus Francavilla vs Audace Cerignola",
    "category_name": "⚽ Soccer"
  },
  {
    "channel_link": "https://d.daddylivehd.sx/embed/stream-9.php",
    "channel_logo": "https://cdn.britannica.com/51/190751-050-147B93F7/soccer-ball-goal.jpg",
    "channels_name": "Cagliari vs Sassuolo",
    "category_name": "⚽ Soccer"
  },
  {
    "channel_link": "https://d.daddylivehd.sx/embed/stream-538.php",
    "channel_logo": "https://cdn.britannica.com/51/190751-050-147B93F7/soccer-ball-goal.jpg",
    "channels_name": "Rayo Vallecano vs Celta de Vigo",
    "category_name": "⚽ Soccer"
  },
  {
    "channel_link": "https://d.daddylivehd.sx/embed/stream-10.php",
    "channel_logo": "https://cdn.britannica.com/51/190751-050-147B93F7/soccer-ball-goal.jpg",
    "channels_name": "Tenerife vs Alcorcón",
    "category_name": "⚽ Soccer"
  },
  {
    "channel_link": "https://d.daddylivehd.sx/embed/stream-49.php",
    "channel_logo": "https://cdn.britannica.com/51/190751-050-147B93F7/soccer-ball-goal.jpg",
    "channels_name": "Gil Vicente vs Moreirense",
    "category_name": "⚽ Soccer"
  },
  {
    "channel_link": "https://d.daddylivehd.sx/embed/stream-316.php",
    "channel_logo": "https://cdn.britannica.com/51/190751-050-147B93F7/soccer-ball-goal.jpg",
    "channels_name": "Notre Dame vs Clemson",
    "category_name": "⚽ Soccer"
  }
]
  
